<?xml version="1.0" encoding="UTF-8"?>
<AnomalyReport_MarketDocument xmlns="urn:iec62325.351:tc57wg16:451-2:anomalydocument:5:0">
    <mRID>20241016-10XDE-EON-NETZ-C-TPS-55407</mRID>
    <createdDateTime>2024-10-16T10:54:41Z</createdDateTime>
    <sender_MarketParticipant.mRID codingScheme="A01">10XDE-EON-NETZ-C</sender_MarketParticipant.mRID>
    <sender_MarketParticipant.marketRole.type>A04</sender_MarketParticipant.marketRole.type>
    <receiver_MarketParticipant.mRID codingScheme="A01">11X0-0000-0706-U</receiver_MarketParticipant.mRID>
    <receiver_MarketParticipant.marketRole.type>A08</receiver_MarketParticipant.marketRole.type><schedule_Time_Period.timeInterval>
    <start>2024-10-15T22:00Z</start>
    <end>2024-10-16T22:00Z</end>
</schedule_Time_Period.timeInterval>
    <domain.mRID codingScheme="A01">10YDE-EON------1</domain.mRID><Anomaly_MarketDocument>
    <marketParticipant.mRID codingScheme="A01">20X-LU005-ECCINI</marketParticipant.mRID>
    <mRID>20X-LU005-ECCIN10YDE-EON------O1016</mRID>
    <revisionNumber>148</revisionNumber>
    <TimeSeries>
        <mRID>rr11X0-0000-0706-Us</mRID>
        <version>68</version>
        <businessType>A02</businessType>
        <product>8716867000016</product>
        <objectAggregation>A01</objectAggregation>
        <in_Domain.mRID codingScheme="A01">10YDE-EON------1</in_Domain.mRID>
        <out_Domain.mRID codingScheme="A01">10YDE-EON------1</out_Domain.mRID>
        <in_MarketParticipant.mRID codingScheme="A01">20X-LU005-ECCINI</in_MarketParticipant.mRID>
        <out_MarketParticipant.mRID codingScheme="A01">11X0-0000-0706-U</out_MarketParticipant.mRID>
        <measurement_Unit.name>MAW</measurement_Unit.name>
        <Period>
            <timeInterval>
                <start>2024-10-15T22:00Z</start>
                <end>2024-10-16T22:00Z</end>
            </timeInterval>
            <resolution>PT15M</resolution>
            <Point>
                <position>1</position>
                <quantity>0.000</quantity>
            </Point>
            <Point>
                <position>2</position>
                <quantity>0.000</quantity>
            </Point>
            <Point>
                <position>3</position>
                <quantity>0.000</quantity>
            </Point>
            <Point>
                <position>4</position>
                <quantity>0.000</quantity>
            </Point>
            <Point>
                <position>5</position>
                <quantity>0.000</quantity>
            </Point>
            <Point>
                <position>6</position>
                <quantity>0.000</quantity>
            </Point>
            <Point>
                <position>7</position>
                <quantity>0.000</quantity>
            </Point>
            <Point>
                <position>8</position>
                <quantity>0.000</quantity>
            </Point>
            <Point>
                <position>9</position>
                <quantity>0.200</quantity>
            </Point>
            <Point>
                <position>10</position>
                <quantity>0.200</quantity>
            </Point>
            <Point>
                <position>11</position>
                <quantity>0.200</quantity>
            </Point>
            <Point>
                <position>12</position>
                <quantity>0.200</quantity>
            </Point>
            <Point>
                <position>13</position>
                <quantity>0.200</quantity>
            </Point>
            <Point>
                <position>14</position>
                <quantity>0.000</quantity>
            </Point>
            <Point>
                <position>15</position>
                <quantity>0.200</quantity>
            </Point>
            <Point>
                <position>16</position>
                <quantity>0.000</quantity>
            </Point>
            <Point>
                <position>17</position>
                <quantity>0.000</quantity>
            </Point>
            <Point>
                <position>18</position>
                <quantity>0.000</quantity>
            </Point>
            <Point>
                <position>19</position>
                <quantity>0.000</quantity>
            </Point>
            <Point>
                <position>20</position>
                <quantity>0.000</quantity>
            </Point>
            <Point>
                <position>21</position>
                <quantity>0.000</quantity>
            </Point>
            <Point>
                <position>22</position>
                <quantity>0.000</quantity>
            </Point>
            <Point>
                <position>23</position>
                <quantity>0.000</quantity>
            </Point>
            <Point>
                <position>24</position>
                <quantity>0.000</quantity>
            </Point>
            <Point>
                <position>25</position>
                <quantity>0.000</quantity>
            </Point>
            <Point>
                <position>26</position>
                <quantity>0.000</quantity>
            </Point>
            <Point>
                <position>27</position>
                <quantity>0.000</quantity>
            </Point>
            <Point>
                <position>28</position>
                <quantity>0.000</quantity>
            </Point>
            <Point>
                <position>29</position>
                <quantity>0.000</quantity>
            </Point>
            <Point>
                <position>30</position>
                <quantity>0.000</quantity>
            </Point>
            <Point>
                <position>31</position>
                <quantity>0.000</quantity>
            </Point>
            <Point>
                <position>32</position>
                <quantity>0.000</quantity>
            </Point>
            <Point>
                <position>33</position>
                <quantity>0.000</quantity>
            </Point>
            <Point>
                <position>34</position>
                <quantity>0.000</quantity>
            </Point>
            <Point>
                <position>35</position>
                <quantity>0.000</quantity>
            </Point>
            <Point>
                <position>36</position>
                <quantity>0.000</quantity>
            </Point>
            <Point>
                <position>37</position>
                <quantity>0.000</quantity>
            </Point>
            <Point>
                <position>38</position>
                <quantity>0.000</quantity>
            </Point>
            <Point>
                <position>39</position>
                <quantity>0.000</quantity>
            </Point>
            <Point>
                <position>40</position>
                <quantity>0.000</quantity>
            </Point>
            <Point>
                <position>41</position>
                <quantity>0.000</quantity>
            </Point>
            <Point>
                <position>42</position>
                <quantity>0.000</quantity>
            </Point>
            <Point>
                <position>43</position>
                <quantity>0.000</quantity>
            </Point>
            <Point>
                <position>44</position>
                <quantity>0.000</quantity>
            </Point>
            <Point>
                <position>45</position>
                <quantity>0.000</quantity>
            </Point>
            <Point>
                <position>46</position>
                <quantity>0.000</quantity>
            </Point>
            <Point>
                <position>47</position>
                <quantity>0.000</quantity>
            </Point>
            <Point>
                <position>48</position>
                <quantity>0.000</quantity>
            </Point>
            <Point>
                <position>49</position>
                <quantity>0.000</quantity>
            </Point>
            <Point>
                <position>50</position>
                <quantity>0.000</quantity>
            </Point>
            <Point>
                <position>51</position>
                <quantity>0.000</quantity>
            </Point>
            <Point>
                <position>52</position>
                <quantity>0.000</quantity>
            </Point>
            <Point>
                <position>53</position>
                <quantity>0.000</quantity>
            </Point>
            <Point>
                <position>54</position>
                <quantity>0.000</quantity>
            </Point>
            <Point>
                <position>55</position>
                <quantity>0.000</quantity>
            </Point>
            <Point>
                <position>56</position>
                <quantity>0.000</quantity>
            </Point>
            <Point>
                <position>57</position>
                <quantity>0.000</quantity>
            </Point>
            <Point>
                <position>58</position>
                <quantity>0.000</quantity>
            </Point>
            <Point>
                <position>59</position>
                <quantity>0.000</quantity>
            </Point>
            <Point>
                <position>60</position>
                <quantity>0.000</quantity>
            </Point>
            <Point>
                <position>61</position>
                <quantity>0.000</quantity>
            </Point>
            <Point>
                <position>62</position>
                <quantity>0.000</quantity>
            </Point>
            <Point>
                <position>63</position>
                <quantity>0.000</quantity>
            </Point>
            <Point>
                <position>64</position>
                <quantity>0.000</quantity>
            </Point>
            <Point>
                <position>65</position>
                <quantity>0.000</quantity>
            </Point>
            <Point>
                <position>66</position>
                <quantity>0.000</quantity>
            </Point>
            <Point>
                <position>67</position>
                <quantity>0.000</quantity>
            </Point>
            <Point>
                <position>68</position>
                <quantity>0.000</quantity>
            </Point>
            <Point>
                <position>69</position>
                <quantity>0.000</quantity>
            </Point>
            <Point>
                <position>70</position>
                <quantity>0.000</quantity>
            </Point>
            <Point>
                <position>71</position>
                <quantity>0.000</quantity>
            </Point>
            <Point>
                <position>72</position>
                <quantity>0.000</quantity>
            </Point>
            <Point>
                <position>73</position>
                <quantity>0.000</quantity>
            </Point>
            <Point>
                <position>74</position>
                <quantity>0.000</quantity>
            </Point>
            <Point>
                <position>75</position>
                <quantity>0.000</quantity>
            </Point>
            <Point>
                <position>76</position>
                <quantity>0.000</quantity>
            </Point>
            <Point>
                <position>77</position>
                <quantity>0.000</quantity>
            </Point>
            <Point>
                <position>78</position>
                <quantity>0.000</quantity>
            </Point>
            <Point>
                <position>79</position>
                <quantity>0.000</quantity>
            </Point>
            <Point>
                <position>80</position>
                <quantity>0.000</quantity>
            </Point>
            <Point>
                <position>81</position>
                <quantity>0.000</quantity>
            </Point>
            <Point>
                <position>82</position>
                <quantity>0.000</quantity>
            </Point>
            <Point>
                <position>83</position>
                <quantity>0.000</quantity>
            </Point>
            <Point>
                <position>84</position>
                <quantity>0.000</quantity>
            </Point>
            <Point>
                <position>85</position>
                <quantity>0.000</quantity>
            </Point>
            <Point>
                <position>86</position>
                <quantity>0.000</quantity>
            </Point>
            <Point>
                <position>87</position>
                <quantity>0.000</quantity>
            </Point>
            <Point>
                <position>88</position>
                <quantity>0.000</quantity>
            </Point>
            <Point>
                <position>89</position>
                <quantity>0.000</quantity>
            </Point>
            <Point>
                <position>90</position>
                <quantity>0.000</quantity>
            </Point>
            <Point>
                <position>91</position>
                <quantity>0.000</quantity>
            </Point>
            <Point>
                <position>92</position>
                <quantity>0.000</quantity>
            </Point>
            <Point>
                <position>93</position>
                <quantity>0.000</quantity>
            </Point>
            <Point>
                <position>94</position>
                <quantity>0.000</quantity>
            </Point>
            <Point>
                <position>95</position>
                <quantity>0.000</quantity>
            </Point>
            <Point>
                <position>96</position>
                <quantity>0.000</quantity>
            </Point>
        </Period>
        <Reason>
            <code>A09</code>
            <text>Beim Vergleich mit der Gegenmeldung trat ein Fehler auf: </text>
        </Reason>
    </TimeSeries>
</Anomaly_MarketDocument>
    <Anomaly_MarketDocument>
        <marketParticipant.mRID codingScheme="A01">20X-LU005-ECCINI</marketParticipant.mRID>
        <mRID>20X-LU005-ECCIN10YDE-EON------O1016</mRID>
        <revisionNumber>148</revisionNumber>
        <TimeSeries>
            <mRID>rrs11X0-0000-0706-U</mRID>
            <version>147</version>
            <businessType>A02</businessType>
            <product>8716867000016</product>
            <objectAggregation>A01</objectAggregation>
            <in_Domain.mRID codingScheme="A01">10YDE-EON------1</in_Domain.mRID>
            <out_Domain.mRID codingScheme="A01">10YDE-EON------1</out_Domain.mRID>
            <in_MarketParticipant.mRID codingScheme="A01">11X0-0000-0706-U</in_MarketParticipant.mRID>
            <out_MarketParticipant.mRID codingScheme="A01">20X-LU005-ECCINI</out_MarketParticipant.mRID>
            <measurement_Unit.name>MAW</measurement_Unit.name>
            <Period>
                <timeInterval>
                    <start>2024-10-15T22:00Z</start>
                    <end>2024-10-16T22:00Z</end>
                </timeInterval>
                <resolution>PT15M</resolution>
                <Point>
                    <position>1</position>
                    <quantity>0.000</quantity>
                </Point>
                <Point>
                    <position>2</position>
                    <quantity>0.000</quantity>
                </Point>
                <Point>
                    <position>3</position>
                    <quantity>0.000</quantity>
                </Point>
                <Point>
                    <position>4</position>
                    <quantity>0.000</quantity>
                </Point>
                <Point>
                    <position>5</position>
                    <quantity>0.000</quantity>
                </Point>
                <Point>
                    <position>6</position>
                    <quantity>0.000</quantity>
                </Point>
                <Point>
                    <position>7</position>
                    <quantity>0.000</quantity>
                </Point>
                <Point>
                    <position>8</position>
                    <quantity>0.000</quantity>
                </Point>
                <Point>
                    <position>9</position>
                    <quantity>0.000</quantity>
                </Point>
                <Point>
                    <position>10</position>
                    <quantity>0.000</quantity>
                </Point>
                <Point>
                    <position>11</position>
                    <quantity>0.000</quantity>
                </Point>
                <Point>
                    <position>12</position>
                    <quantity>0.000</quantity>
                </Point>
                <Point>
                    <position>13</position>
                    <quantity>0.000</quantity>
                </Point>
                <Point>
                    <position>14</position>
                    <quantity>0.700</quantity>
                </Point>
                <Point>
                    <position>15</position>
                    <quantity>0.000</quantity>
                </Point>
                <Point>
                    <position>16</position>
                    <quantity>0.700</quantity>
                </Point>
                <Point>
                    <position>17</position>
                    <quantity>1.800</quantity>
                </Point>
                <Point>
                    <position>18</position>
                    <quantity>1.800</quantity>
                </Point>
                <Point>
                    <position>19</position>
                    <quantity>1.300</quantity>
                </Point>
                <Point>
                    <position>20</position>
                    <quantity>1.200</quantity>
                </Point>
                <Point>
                    <position>21</position>
                    <quantity>1.300</quantity>
                </Point>
                <Point>
                    <position>22</position>
                    <quantity>1.100</quantity>
                </Point>
                <Point>
                    <position>23</position>
                    <quantity>1.200</quantity>
                </Point>
                <Point>
                    <position>24</position>
                    <quantity>1.400</quantity>
                </Point>
                <Point>
                    <position>25</position>
                    <quantity>1.300</quantity>
                </Point>
                <Point>
                    <position>26</position>
                    <quantity>1.400</quantity>
                </Point>
                <Point>
                    <position>27</position>
                    <quantity>1.300</quantity>
                </Point>
                <Point>
                    <position>28</position>
                    <quantity>1.300</quantity>
                </Point>
                <Point>
                    <position>29</position>
                    <quantity>1.400</quantity>
                </Point>
                <Point>
                    <position>30</position>
                    <quantity>1.300</quantity>
                </Point>
                <Point>
                    <position>31</position>
                    <quantity>1.400</quantity>
                </Point>
                <Point>
                    <position>32</position>
                    <quantity>1.400</quantity>
                </Point>
                <Point>
                    <position>33</position>
                    <quantity>1.200</quantity>
                </Point>
                <Point>
                    <position>34</position>
                    <quantity>1.000</quantity>
                </Point>
                <Point>
                    <position>35</position>
                    <quantity>0.800</quantity>
                </Point>
                <Point>
                    <position>36</position>
                    <quantity>0.800</quantity>
                </Point>
                <Point>
                    <position>37</position>
                    <quantity>0.700</quantity>
                </Point>
                <Point>
                    <position>38</position>
                    <quantity>0.500</quantity>
                </Point>
                <Point>
                    <position>39</position>
                    <quantity>0.400</quantity>
                </Point>
                <Point>
                    <position>40</position>
                    <quantity>0.400</quantity>
                </Point>
                <Point>
                    <position>41</position>
                    <quantity>0.700</quantity>
                </Point>
                <Point>
                    <position>42</position>
                    <quantity>0.800</quantity>
                </Point>
                <Point>
                    <position>43</position>
                    <quantity>0.700</quantity>
                </Point>
                <Point>
                    <position>44</position>
                    <quantity>0.600</quantity>
                </Point>
                <Point>
                    <position>45</position>
                    <quantity>0.600</quantity>
                </Point>
                <Point>
                    <position>46</position>
                    <quantity>0.600</quantity>
                </Point>
                <Point>
                    <position>47</position>
                    <quantity>0.600</quantity>
                </Point>
                <Point>
                    <position>48</position>
                    <quantity>0.700</quantity>
                </Point>
                <Point>
                    <position>49</position>
                    <quantity>0.600</quantity>
                </Point>
                <Point>
                    <position>50</position>
                    <quantity>0.700</quantity>
                </Point>
                <Point>
                    <position>51</position>
                    <quantity>0.400</quantity>
                </Point>
                <Point>
                    <position>52</position>
                    <quantity>0.400</quantity>
                </Point>
                <Point>
                    <position>53</position>
                    <quantity>0.300</quantity>
                </Point>
                <Point>
                    <position>54</position>
                    <quantity>0.300</quantity>
                </Point>
                <Point>
                    <position>55</position>
                    <quantity>0.300</quantity>
                </Point>
                <Point>
                    <position>56</position>
                    <quantity>0.300</quantity>
                </Point>
                <Point>
                    <position>57</position>
                    <quantity>0.300</quantity>
                </Point>
                <Point>
                    <position>58</position>
                    <quantity>0.300</quantity>
                </Point>
                <Point>
                    <position>59</position>
                    <quantity>0.300</quantity>
                </Point>
                <Point>
                    <position>60</position>
                    <quantity>0.300</quantity>
                </Point>
                <Point>
                    <position>61</position>
                    <quantity>0.000</quantity>
                </Point>
                <Point>
                    <position>62</position>
                    <quantity>0.000</quantity>
                </Point>
                <Point>
                    <position>63</position>
                    <quantity>0.000</quantity>
                </Point>
                <Point>
                    <position>64</position>
                    <quantity>0.000</quantity>
                </Point>
                <Point>
                    <position>65</position>
                    <quantity>0.000</quantity>
                </Point>
                <Point>
                    <position>66</position>
                    <quantity>0.000</quantity>
                </Point>
                <Point>
                    <position>67</position>
                    <quantity>0.000</quantity>
                </Point>
                <Point>
                    <position>68</position>
                    <quantity>0.000</quantity>
                </Point>
                <Point>
                    <position>69</position>
                    <quantity>0.000</quantity>
                </Point>
                <Point>
                    <position>70</position>
                    <quantity>0.000</quantity>
                </Point>
                <Point>
                    <position>71</position>
                    <quantity>0.000</quantity>
                </Point>
                <Point>
                    <position>72</position>
                    <quantity>0.000</quantity>
                </Point>
                <Point>
                    <position>73</position>
                    <quantity>0.000</quantity>
                </Point>
                <Point>
                    <position>74</position>
                    <quantity>0.000</quantity>
                </Point>
                <Point>
                    <position>75</position>
                    <quantity>0.000</quantity>
                </Point>
                <Point>
                    <position>76</position>
                    <quantity>0.000</quantity>
                </Point>
                <Point>
                    <position>77</position>
                    <quantity>0.000</quantity>
                </Point>
                <Point>
                    <position>78</position>
                    <quantity>0.000</quantity>
                </Point>
                <Point>
                    <position>79</position>
                    <quantity>0.000</quantity>
                </Point>
                <Point>
                    <position>80</position>
                    <quantity>0.000</quantity>
                </Point>
                <Point>
                    <position>81</position>
                    <quantity>0.000</quantity>
                </Point>
                <Point>
                    <position>82</position>
                    <quantity>0.000</quantity>
                </Point>
                <Point>
                    <position>83</position>
                    <quantity>0.000</quantity>
                </Point>
                <Point>
                    <position>84</position>
                    <quantity>0.000</quantity>
                </Point>
                <Point>
                    <position>85</position>
                    <quantity>0.000</quantity>
                </Point>
                <Point>
                    <position>86</position>
                    <quantity>0.000</quantity>
                </Point>
                <Point>
                    <position>87</position>
                    <quantity>0.000</quantity>
                </Point>
                <Point>
                    <position>88</position>
                    <quantity>0.000</quantity>
                </Point>
                <Point>
                    <position>89</position>
                    <quantity>0.000</quantity>
                </Point>
                <Point>
                    <position>90</position>
                    <quantity>0.000</quantity>
                </Point>
                <Point>
                    <position>91</position>
                    <quantity>0.000</quantity>
                </Point>
                <Point>
                    <position>92</position>
                    <quantity>0.000</quantity>
                </Point>
                <Point>
                    <position>93</position>
                    <quantity>0.000</quantity>
                </Point>
                <Point>
                    <position>94</position>
                    <quantity>0.000</quantity>
                </Point>
                <Point>
                    <position>95</position>
                    <quantity>0.000</quantity>
                </Point>
                <Point>
                    <position>96</position>
                    <quantity>0.000</quantity>
                </Point>
            </Period>
            <Reason>
                <code>A09</code>
                <text>Beim Vergleich mit der Gegenmeldung trat ein Fehler auf: </text>
            </Reason>
        </TimeSeries>
    </Anomaly_MarketDocument>
    <Anomaly_MarketDocument>
        <marketParticipant.mRID codingScheme="A01">11X0-0000-0706-U</marketParticipant.mRID>
        <mRID>241016_X0-0000-0706-_XDE-EON-NE</mRID>
        <revisionNumber>103</revisionNumber>
        <TimeSeries>
            <mRID>rr20X-LU005-ECCINIs</mRID>
            <version>103</version>
            <businessType>A02</businessType>
            <product>8716867000016</product>
            <objectAggregation>A01</objectAggregation>
            <in_Domain.mRID codingScheme="A01">10YDE-EON------1</in_Domain.mRID>
            <out_Domain.mRID codingScheme="A01">10YDE-EON------1</out_Domain.mRID>
            <in_MarketParticipant.mRID codingScheme="A01">11X0-0000-0706-U</in_MarketParticipant.mRID>
            <out_MarketParticipant.mRID codingScheme="A01">20X-LU005-ECCINI</out_MarketParticipant.mRID>
            <measurement_Unit.name>MAW</measurement_Unit.name>
            <Period>
                <timeInterval>
                    <start>2024-10-15T22:00Z</start>
                    <end>2024-10-16T22:00Z</end>
                </timeInterval>
                <resolution>PT15M</resolution>
                <Point>
                    <position>1</position>
                    <quantity>0.000</quantity>
                </Point>
                <Point>
                    <position>2</position>
                    <quantity>0.000</quantity>
                </Point>
                <Point>
                    <position>3</position>
                    <quantity>0.000</quantity>
                </Point>
                <Point>
                    <position>4</position>
                    <quantity>0.000</quantity>
                </Point>
                <Point>
                    <position>5</position>
                    <quantity>0.000</quantity>
                </Point>
                <Point>
                    <position>6</position>
                    <quantity>0.000</quantity>
                </Point>
                <Point>
                    <position>7</position>
                    <quantity>0.000</quantity>
                </Point>
                <Point>
                    <position>8</position>
                    <quantity>0.000</quantity>
                </Point>
                <Point>
                    <position>9</position>
                    <quantity>0.000</quantity>
                </Point>
                <Point>
                    <position>10</position>
                    <quantity>0.000</quantity>
                </Point>
                <Point>
                    <position>11</position>
                    <quantity>0.000</quantity>
                </Point>
                <Point>
                    <position>12</position>
                    <quantity>0.000</quantity>
                </Point>
                <Point>
                    <position>13</position>
                    <quantity>0.000</quantity>
                </Point>
                <Point>
                    <position>14</position>
                    <quantity>0.700</quantity>
                </Point>
                <Point>
                    <position>15</position>
                    <quantity>0.000</quantity>
                </Point>
                <Point>
                    <position>16</position>
                    <quantity>0.700</quantity>
                </Point>
                <Point>
                    <position>17</position>
                    <quantity>1.800</quantity>
                </Point>
                <Point>
                    <position>18</position>
                    <quantity>1.800</quantity>
                </Point>
                <Point>
                    <position>19</position>
                    <quantity>1.300</quantity>
                </Point>
                <Point>
                    <position>20</position>
                    <quantity>1.200</quantity>
                </Point>
                <Point>
                    <position>21</position>
                    <quantity>1.300</quantity>
                </Point>
                <Point>
                    <position>22</position>
                    <quantity>1.100</quantity>
                </Point>
                <Point>
                    <position>23</position>
                    <quantity>1.200</quantity>
                </Point>
                <Point>
                    <position>24</position>
                    <quantity>1.400</quantity>
                </Point>
                <Point>
                    <position>25</position>
                    <quantity>1.300</quantity>
                </Point>
                <Point>
                    <position>26</position>
                    <quantity>1.400</quantity>
                </Point>
                <Point>
                    <position>27</position>
                    <quantity>1.300</quantity>
                </Point>
                <Point>
                    <position>28</position>
                    <quantity>1.300</quantity>
                </Point>
                <Point>
                    <position>29</position>
                    <quantity>1.400</quantity>
                </Point>
                <Point>
                    <position>30</position>
                    <quantity>1.300</quantity>
                </Point>
                <Point>
                    <position>31</position>
                    <quantity>1.400</quantity>
                </Point>
                <Point>
                    <position>32</position>
                    <quantity>1.400</quantity>
                </Point>
                <Point>
                    <position>33</position>
                    <quantity>1.200</quantity>
                </Point>
                <Point>
                    <position>34</position>
                    <quantity>1.000</quantity>
                </Point>
                <Point>
                    <position>35</position>
                    <quantity>0.800</quantity>
                </Point>
                <Point>
                    <position>36</position>
                    <quantity>0.800</quantity>
                </Point>
                <Point>
                    <position>37</position>
                    <quantity>0.700</quantity>
                </Point>
                <Point>
                    <position>38</position>
                    <quantity>0.500</quantity>
                </Point>
                <Point>
                    <position>39</position>
                    <quantity>0.400</quantity>
                </Point>
                <Point>
                    <position>40</position>
                    <quantity>0.400</quantity>
                </Point>
                <Point>
                    <position>41</position>
                    <quantity>0.700</quantity>
                </Point>
                <Point>
                    <position>42</position>
                    <quantity>0.800</quantity>
                </Point>
                <Point>
                    <position>43</position>
                    <quantity>0.700</quantity>
                </Point>
                <Point>
                    <position>44</position>
                    <quantity>0.600</quantity>
                </Point>
                <Point>
                    <position>45</position>
                    <quantity>0.600</quantity>
                </Point>
                <Point>
                    <position>46</position>
                    <quantity>0.600</quantity>
                </Point>
                <Point>
                    <position>47</position>
                    <quantity>0.600</quantity>
                </Point>
                <Point>
                    <position>48</position>
                    <quantity>0.700</quantity>
                </Point>
                <Point>
                    <position>49</position>
                    <quantity>0.600</quantity>
                </Point>
                <Point>
                    <position>50</position>
                    <quantity>0.700</quantity>
                </Point>
                <Point>
                    <position>51</position>
                    <quantity>0.400</quantity>
                </Point>
                <Point>
                    <position>52</position>
                    <quantity>0.400</quantity>
                </Point>
                <Point>
                    <position>53</position>
                    <quantity>0.300</quantity>
                </Point>
                <Point>
                    <position>54</position>
                    <quantity>0.300</quantity>
                </Point>
                <Point>
                    <position>55</position>
                    <quantity>0.300</quantity>
                </Point>
                <Point>
                    <position>56</position>
                    <quantity>0.300</quantity>
                </Point>
                <Point>
                    <position>57</position>
                    <quantity>0.100</quantity>
                </Point>
                <Point>
                    <position>58</position>
                    <quantity>0.100</quantity>
                </Point>
                <Point>
                    <position>59</position>
                    <quantity>0.100</quantity>
                </Point>
                <Point>
                    <position>60</position>
                    <quantity>0.100</quantity>
                </Point>
                <Point>
                    <position>61</position>
                    <quantity>0.000</quantity>
                </Point>
                <Point>
                    <position>62</position>
                    <quantity>0.000</quantity>
                </Point>
                <Point>
                    <position>63</position>
                    <quantity>0.000</quantity>
                </Point>
                <Point>
                    <position>64</position>
                    <quantity>0.000</quantity>
                </Point>
                <Point>
                    <position>65</position>
                    <quantity>0.000</quantity>
                </Point>
                <Point>
                    <position>66</position>
                    <quantity>0.000</quantity>
                </Point>
                <Point>
                    <position>67</position>
                    <quantity>0.000</quantity>
                </Point>
                <Point>
                    <position>68</position>
                    <quantity>0.000</quantity>
                </Point>
                <Point>
                    <position>69</position>
                    <quantity>0.000</quantity>
                </Point>
                <Point>
                    <position>70</position>
                    <quantity>0.000</quantity>
                </Point>
                <Point>
                    <position>71</position>
                    <quantity>0.000</quantity>
                </Point>
                <Point>
                    <position>72</position>
                    <quantity>0.000</quantity>
                </Point>
                <Point>
                    <position>73</position>
                    <quantity>0.000</quantity>
                </Point>
                <Point>
                    <position>74</position>
                    <quantity>0.000</quantity>
                </Point>
                <Point>
                    <position>75</position>
                    <quantity>0.000</quantity>
                </Point>
                <Point>
                    <position>76</position>
                    <quantity>0.000</quantity>
                </Point>
                <Point>
                    <position>77</position>
                    <quantity>0.000</quantity>
                </Point>
                <Point>
                    <position>78</position>
                    <quantity>0.000</quantity>
                </Point>
                <Point>
                    <position>79</position>
                    <quantity>0.000</quantity>
                </Point>
                <Point>
                    <position>80</position>
                    <quantity>0.000</quantity>
                </Point>
                <Point>
                    <position>81</position>
                    <quantity>0.000</quantity>
                </Point>
                <Point>
                    <position>82</position>
                    <quantity>0.000</quantity>
                </Point>
                <Point>
                    <position>83</position>
                    <quantity>0.000</quantity>
                </Point>
                <Point>
                    <position>84</position>
                    <quantity>0.000</quantity>
                </Point>
                <Point>
                    <position>85</position>
                    <quantity>0.000</quantity>
                </Point>
                <Point>
                    <position>86</position>
                    <quantity>0.000</quantity>
                </Point>
                <Point>
                    <position>87</position>
                    <quantity>0.000</quantity>
                </Point>
                <Point>
                    <position>88</position>
                    <quantity>0.000</quantity>
                </Point>
                <Point>
                    <position>89</position>
                    <quantity>0.000</quantity>
                </Point>
                <Point>
                    <position>90</position>
                    <quantity>0.000</quantity>
                </Point>
                <Point>
                    <position>91</position>
                    <quantity>0.000</quantity>
                </Point>
                <Point>
                    <position>92</position>
                    <quantity>0.000</quantity>
                </Point>
                <Point>
                    <position>93</position>
                    <quantity>0.000</quantity>
                </Point>
                <Point>
                    <position>94</position>
                    <quantity>0.000</quantity>
                </Point>
                <Point>
                    <position>95</position>
                    <quantity>0.000</quantity>
                </Point>
                <Point>
                    <position>96</position>
                    <quantity>0.000</quantity>
                </Point>
            </Period>
            <Reason>
                <code>A09</code>
                <text>Beim Vergleich mit der Gegenmeldung trat ein Fehler auf: </text>
            </Reason>
        </TimeSeries>
    </Anomaly_MarketDocument>
    <Anomaly_MarketDocument>
        <marketParticipant.mRID codingScheme="A01">11X0-0000-0706-U</marketParticipant.mRID>
        <mRID>241016_X0-0000-0706-_XDE-EON-NE</mRID>
        <revisionNumber>103</revisionNumber>
        <TimeSeries>
            <mRID>rrs20X-LU005-ECCINI</mRID>
            <version>101</version>
            <businessType>A02</businessType>
            <product>8716867000016</product>
            <objectAggregation>A01</objectAggregation>
            <in_Domain.mRID codingScheme="A01">10YDE-EON------1</in_Domain.mRID>
            <out_Domain.mRID codingScheme="A01">10YDE-EON------1</out_Domain.mRID>
            <in_MarketParticipant.mRID codingScheme="A01">20X-LU005-ECCINI</in_MarketParticipant.mRID>
            <out_MarketParticipant.mRID codingScheme="A01">11X0-0000-0706-U</out_MarketParticipant.mRID>
            <measurement_Unit.name>MAW</measurement_Unit.name>
            <Period>
                <timeInterval>
                    <start>2024-10-15T22:00Z</start>
                    <end>2024-10-16T22:00Z</end>
                </timeInterval>
                <resolution>PT15M</resolution>
                <Point>
                    <position>1</position>
                    <quantity>0.000</quantity>
                </Point>
                <Point>
                    <position>2</position>
                    <quantity>0.000</quantity>
                </Point>
                <Point>
                    <position>3</position>
                    <quantity>0.000</quantity>
                </Point>
                <Point>
                    <position>4</position>
                    <quantity>0.000</quantity>
                </Point>
                <Point>
                    <position>5</position>
                    <quantity>0.000</quantity>
                </Point>
                <Point>
                    <position>6</position>
                    <quantity>0.000</quantity>
                </Point>
                <Point>
                    <position>7</position>
                    <quantity>0.000</quantity>
                </Point>
                <Point>
                    <position>8</position>
                    <quantity>0.000</quantity>
                </Point>
                <Point>
                    <position>9</position>
                    <quantity>0.200</quantity>
                </Point>
                <Point>
                    <position>10</position>
                    <quantity>0.200</quantity>
                </Point>
                <Point>
                    <position>11</position>
                    <quantity>0.200</quantity>
                </Point>
                <Point>
                    <position>12</position>
                    <quantity>0.200</quantity>
                </Point>
                <Point>
                    <position>13</position>
                    <quantity>0.200</quantity>
                </Point>
                <Point>
                    <position>14</position>
                    <quantity>0.000</quantity>
                </Point>
                <Point>
                    <position>15</position>
                    <quantity>0.200</quantity>
                </Point>
                <Point>
                    <position>16</position>
                    <quantity>0.000</quantity>
                </Point>
                <Point>
                    <position>17</position>
                    <quantity>0.000</quantity>
                </Point>
                <Point>
                    <position>18</position>
                    <quantity>0.000</quantity>
                </Point>
                <Point>
                    <position>19</position>
                    <quantity>0.000</quantity>
                </Point>
                <Point>
                    <position>20</position>
                    <quantity>0.000</quantity>
                </Point>
                <Point>
                    <position>21</position>
                    <quantity>0.000</quantity>
                </Point>
                <Point>
                    <position>22</position>
                    <quantity>0.000</quantity>
                </Point>
                <Point>
                    <position>23</position>
                    <quantity>0.000</quantity>
                </Point>
                <Point>
                    <position>24</position>
                    <quantity>0.000</quantity>
                </Point>
                <Point>
                    <position>25</position>
                    <quantity>0.000</quantity>
                </Point>
                <Point>
                    <position>26</position>
                    <quantity>0.000</quantity>
                </Point>
                <Point>
                    <position>27</position>
                    <quantity>0.000</quantity>
                </Point>
                <Point>
                    <position>28</position>
                    <quantity>0.000</quantity>
                </Point>
                <Point>
                    <position>29</position>
                    <quantity>0.000</quantity>
                </Point>
                <Point>
                    <position>30</position>
                    <quantity>0.000</quantity>
                </Point>
                <Point>
                    <position>31</position>
                    <quantity>0.000</quantity>
                </Point>
                <Point>
                    <position>32</position>
                    <quantity>0.000</quantity>
                </Point>
                <Point>
                    <position>33</position>
                    <quantity>0.000</quantity>
                </Point>
                <Point>
                    <position>34</position>
                    <quantity>0.000</quantity>
                </Point>
                <Point>
                    <position>35</position>
                    <quantity>0.000</quantity>
                </Point>
                <Point>
                    <position>36</position>
                    <quantity>0.000</quantity>
                </Point>
                <Point>
                    <position>37</position>
                    <quantity>0.000</quantity>
                </Point>
                <Point>
                    <position>38</position>
                    <quantity>0.000</quantity>
                </Point>
                <Point>
                    <position>39</position>
                    <quantity>0.000</quantity>
                </Point>
                <Point>
                    <position>40</position>
                    <quantity>0.000</quantity>
                </Point>
                <Point>
                    <position>41</position>
                    <quantity>0.000</quantity>
                </Point>
                <Point>
                    <position>42</position>
                    <quantity>0.000</quantity>
                </Point>
                <Point>
                    <position>43</position>
                    <quantity>0.000</quantity>
                </Point>
                <Point>
                    <position>44</position>
                    <quantity>0.000</quantity>
                </Point>
                <Point>
                    <position>45</position>
                    <quantity>0.000</quantity>
                </Point>
                <Point>
                    <position>46</position>
                    <quantity>0.000</quantity>
                </Point>
                <Point>
                    <position>47</position>
                    <quantity>0.000</quantity>
                </Point>
                <Point>
                    <position>48</position>
                    <quantity>0.000</quantity>
                </Point>
                <Point>
                    <position>49</position>
                    <quantity>0.000</quantity>
                </Point>
                <Point>
                    <position>50</position>
                    <quantity>0.000</quantity>
                </Point>
                <Point>
                    <position>51</position>
                    <quantity>0.000</quantity>
                </Point>
                <Point>
                    <position>52</position>
                    <quantity>0.000</quantity>
                </Point>
                <Point>
                    <position>53</position>
                    <quantity>0.000</quantity>
                </Point>
                <Point>
                    <position>54</position>
                    <quantity>0.000</quantity>
                </Point>
                <Point>
                    <position>55</position>
                    <quantity>0.000</quantity>
                </Point>
                <Point>
                    <position>56</position>
                    <quantity>0.000</quantity>
                </Point>
                <Point>
                    <position>57</position>
                    <quantity>0.000</quantity>
                </Point>
                <Point>
                    <position>58</position>
                    <quantity>0.000</quantity>
                </Point>
                <Point>
                    <position>59</position>
                    <quantity>0.000</quantity>
                </Point>
                <Point>
                    <position>60</position>
                    <quantity>0.000</quantity>
                </Point>
                <Point>
                    <position>61</position>
                    <quantity>0.000</quantity>
                </Point>
                <Point>
                    <position>62</position>
                    <quantity>0.000</quantity>
                </Point>
                <Point>
                    <position>63</position>
                    <quantity>0.000</quantity>
                </Point>
                <Point>
                    <position>64</position>
                    <quantity>0.000</quantity>
                </Point>
                <Point>
                    <position>65</position>
                    <quantity>0.000</quantity>
                </Point>
                <Point>
                    <position>66</position>
                    <quantity>0.000</quantity>
                </Point>
                <Point>
                    <position>67</position>
                    <quantity>0.000</quantity>
                </Point>
                <Point>
                    <position>68</position>
                    <quantity>0.000</quantity>
                </Point>
                <Point>
                    <position>69</position>
                    <quantity>0.000</quantity>
                </Point>
                <Point>
                    <position>70</position>
                    <quantity>0.000</quantity>
                </Point>
                <Point>
                    <position>71</position>
                    <quantity>0.000</quantity>
                </Point>
                <Point>
                    <position>72</position>
                    <quantity>0.000</quantity>
                </Point>
                <Point>
                    <position>73</position>
                    <quantity>0.000</quantity>
                </Point>
                <Point>
                    <position>74</position>
                    <quantity>0.000</quantity>
                </Point>
                <Point>
                    <position>75</position>
                    <quantity>0.000</quantity>
                </Point>
                <Point>
                    <position>76</position>
                    <quantity>0.000</quantity>
                </Point>
                <Point>
                    <position>77</position>
                    <quantity>0.000</quantity>
                </Point>
                <Point>
                    <position>78</position>
                    <quantity>0.000</quantity>
                </Point>
                <Point>
                    <position>79</position>
                    <quantity>0.000</quantity>
                </Point>
                <Point>
                    <position>80</position>
                    <quantity>0.000</quantity>
                </Point>
                <Point>
                    <position>81</position>
                    <quantity>0.000</quantity>
                </Point>
                <Point>
                    <position>82</position>
                    <quantity>0.000</quantity>
                </Point>
                <Point>
                    <position>83</position>
                    <quantity>0.000</quantity>
                </Point>
                <Point>
                    <position>84</position>
                    <quantity>0.000</quantity>
                </Point>
                <Point>
                    <position>85</position>
                    <quantity>0.000</quantity>
                </Point>
                <Point>
                    <position>86</position>
                    <quantity>0.000</quantity>
                </Point>
                <Point>
                    <position>87</position>
                    <quantity>0.000</quantity>
                </Point>
                <Point>
                    <position>88</position>
                    <quantity>0.000</quantity>
                </Point>
                <Point>
                    <position>89</position>
                    <quantity>0.000</quantity>
                </Point>
                <Point>
                    <position>90</position>
                    <quantity>0.000</quantity>
                </Point>
                <Point>
                    <position>91</position>
                    <quantity>0.000</quantity>
                </Point>
                <Point>
                    <position>92</position>
                    <quantity>0.000</quantity>
                </Point>
                <Point>
                    <position>93</position>
                    <quantity>0.000</quantity>
                </Point>
                <Point>
                    <position>94</position>
                    <quantity>0.000</quantity>
                </Point>
                <Point>
                    <position>95</position>
                    <quantity>0.000</quantity>
                </Point>
                <Point>
                    <position>96</position>
                    <quantity>0.000</quantity>
                </Point>
            </Period>
            <Reason>
                <code>A09</code>
                <text>Beim Vergleich mit der Gegenmeldung trat ein Fehler auf: </text>
            </Reason>
        </TimeSeries>
    </Anomaly_MarketDocument>
</AnomalyReport_MarketDocument>